LICENSE
MANIFEST.in
NOTICE
README.rst
setup.py
dj_webmachine.egg-info/PKG-INFO
dj_webmachine.egg-info/SOURCES.txt
dj_webmachine.egg-info/dependency_links.txt
dj_webmachine.egg-info/not-zip-safe
dj_webmachine.egg-info/requires.txt
dj_webmachine.egg-info/top_level.txt
webmachine/__init__.py
webmachine/api.py
webmachine/exc.py
webmachine/forms.py
webmachine/managers.py
webmachine/models.py
webmachine/throttle.py
webmachine/auth/__init__.py
webmachine/auth/base.py
webmachine/auth/oauth.py
webmachine/auth/oauth_res.py
webmachine/auth/oauth_store.py
webmachine/http/__init__.py
webmachine/http/acceptparse.py
webmachine/http/decisions.py
webmachine/http/etag.py
webmachine/resource/__init__.py
webmachine/resource/base.py
webmachine/templates/webmachine/authorize_token.html
webmachine/util/__init__.py
webmachine/util/const.py
webmachine/util/datetime_util.py